rivia_es_cloud/__init__.py
rivia_es_cloud/_version.py
rivia_es_cloud/main.py
rivia_es_cloud-1.3.1.dist-info/LICENSE
rivia_es_cloud-1.3.1.dist-info/METADATA
rivia_es_cloud-1.3.1.dist-info/WHEEL
rivia_es_cloud-1.3.1.dist-info/top_level.txt
rivia_es_cloud-1.3.1.dist-info/RECORD
