Metadata-Version: 2.1
Name: rivia_es_cloud
Version: 1.3.1
Summary: Wrapper for Elasticsearch cloud client with query builder and improvements
Author-email: Rivia Backend Team <backend@riviadev.com.br>
License: MIT License
Keywords: elasticsearch,cloud,query-builder,python
Classifier: Development Status :: 3 - Alpha
Classifier: Programming Language :: Python :: 3.8
Classifier: License :: OSI Approved :: MIT License
Classifier: Operating System :: OS Independent
Requires-Python: >=3.8
License-File: LICENSE
Requires-Dist: elasticsearch<10.0.0,>=8.15.0
